metodebibliotek/__init__.py
metodebibliotek/metodebibliotek.py
metodebibliotek-0.1.0.dist-info/LICENSE
metodebibliotek-0.1.0.dist-info/METADATA
metodebibliotek-0.1.0.dist-info/WHEEL
metodebibliotek-0.1.0.dist-info/top_level.txt
metodebibliotek-0.1.0.dist-info/RECORD
