Metadata-Version: 2.1
Name: metodebibliotek
Version: 0.1.0
Summary: SSBs library for method functions
Home-page: https://github.com/statisticsnorway/metodebibliotek
Maintainer: Susie Jentoft
Maintainer-email: susiejentoft@ssb.no
License: UNKNOWN
Platform: UNKNOWN
Requires-Python: >=3.6
Requires-Dist: requires
Requires-Dist: numpy
Requires-Dist: pandas
Requires-Dist: datetime
